examples/__init__.py
examples/drf_renderer.py
puppeteer_pdf/__init__.py
puppeteer_pdf/models.py
puppeteer_pdf/utils.py
puppeteer_pdf/views.py
puppeteer_pdf/tests/__init__.py
puppeteer_pdf/tests/models.py
puppeteer_pdf/tests/run.py
puppeteer_pdf/tests/tests.py
puppeteer_pdf/tests/templates/footer.html
puppeteer_pdf/tests/templates/sample.html
puppeteer_pdf/tests/templates/unicode.html
django_puppeteer_pdf-0.1.4.dist-info/LICENSE
django_puppeteer_pdf-0.1.4.dist-info/METADATA
django_puppeteer_pdf-0.1.4.dist-info/WHEEL
django_puppeteer_pdf-0.1.4.dist-info/top_level.txt
django_puppeteer_pdf-0.1.4.dist-info/RECORD
