Metadata-Version: 2.1
Name: django-puppeteer-pdf
Version: 0.1.4
Summary: Converts HTML to PDF using puppeteer.
Home-page: https://github.com/incuna/django-puppeteer-pdf
Author: Namespace
Author-email: admin@incuna.com
License: BSD-2-Clause
Keywords: django puppeteer pdf
Platform: UNKNOWN
Classifier: Development Status :: 5 - Production/Stable
Classifier: Environment :: Web Environment
Classifier: Intended Audience :: Developers
Classifier: Operating System :: OS Independent
Classifier: License :: OSI Approved :: MIT License
Classifier: Programming Language :: Python :: 2
Classifier: Programming Language :: Python :: 2.6
Classifier: Programming Language :: Python :: 2.7
Classifier: Programming Language :: Python :: 3
Classifier: Programming Language :: Python :: 3.3
Classifier: Programming Language :: Python :: 3.4
Classifier: Framework :: Django
